nedo_vision_training/__init__.py
nedo_vision_training/cli.py
nedo_vision_training/doctor.py
nedo_vision_training/exceptions.py
nedo_vision_training/training_service.py
nedo_vision_training/client/ConnectionInfoClient.py
nedo_vision_training/client/DatasetServiceClient.py
nedo_vision_training/client/GrpcClientBase.py
nedo_vision_training/client/RabbitMQClient.py
nedo_vision_training/client/S3Client.py
nedo_vision_training/client/SystemUsageClient.py
nedo_vision_training/client/TrainingAgentStatusClient.py
nedo_vision_training/client/TrainingLoggerClient.py
nedo_vision_training/initializer/AppInitializer.py
nedo_vision_training/logger/Logger.py
nedo_vision_training/logger/TrainerLogger.py
nedo_vision_training/modules/algorithm/RFDETR/RFDETRMetricsCallback.py
nedo_vision_training/modules/algorithm/RFDETR/RFDETRTrainer.py
nedo_vision_training/modules/data_sync/SystemUsageManager.py
nedo_vision_training/modules/dataset/COCODatasetHandler.py
nedo_vision_training/modules/dataset/DatasetHandler.py
nedo_vision_training/modules/trainer/BaseTrainer.py
nedo_vision_training/modules/trainer/Trainer.py
nedo_vision_training/modules/trainer/TrainerFactory.py
nedo_vision_training/modules/trainer/TrainerParams.py
nedo_vision_training/modules/trainer/TrainerRegistry.py
nedo_vision_training/protos/DatasetService.proto
nedo_vision_training/protos/DatasetService_pb2.py
nedo_vision_training/protos/DatasetService_pb2_grpc.py
nedo_vision_training/protos/TrainingAgentService.proto
nedo_vision_training/protos/TrainingAgentService_pb2.py
nedo_vision_training/protos/TrainingAgentService_pb2_grpc.py
nedo_vision_training/protos/TrainingJobService.proto
nedo_vision_training/protos/TrainingJobService_pb2.py
nedo_vision_training/protos/TrainingJobService_pb2_grpc.py
nedo_vision_training/services/DataSenderWorker.py
nedo_vision_training/services/WorkerManager.py
nedo_vision_training/utils/file_utils.py
nedo_vision_training/utils/hardware_id.py
nedo_vision_training/utils/networking.py
nedo_vision_training-1.2.1.dist-info/METADATA
nedo_vision_training-1.2.1.dist-info/WHEEL
nedo_vision_training-1.2.1.dist-info/entry_points.txt
nedo_vision_training-1.2.1.dist-info/top_level.txt
nedo_vision_training-1.2.1.dist-info/RECORD
