Metadata-Version: 2.4
Name: nedo-vision-training
Version: 1.2.1
Summary: A comprehensive training service library for AI models in the Nedo Vision platform
Author-email: Willy Achmat Fauzi <willy.achmat@gmail.com>
Maintainer-email: Willy Achmat Fauzi <willy.achmat@gmail.com>
License-Expression: MIT
Project-URL: Homepage, https://gitlab.com/sindika/research/nedo-vision/nedo-vision-training-service
Project-URL: Documentation, https://gitlab.com/sindika/research/nedo-vision/nedo-vision-training-service/-/blob/main/README.md
Project-URL: Repository, https://gitlab.com/sindika/research/nedo-vision/nedo-vision-training-service
Project-URL: Bug Reports, https://gitlab.com/sindika/research/nedo-vision/nedo-vision-training-service/-/issues
Keywords: computer-vision,machine-learning,ai,training,deep-learning,object-detection,neural-networks,pytorch
Classifier: Development Status :: 4 - Beta
Classifier: Intended Audience :: Developers
Classifier: Programming Language :: Python :: 3
Classifier: Programming Language :: Python :: 3 :: Only
Classifier: Topic :: Scientific/Engineering :: Artificial Intelligence
Requires-Python: >=3.10
Requires-Dist: grpcio<2.0.0,>=1.59.0
Requires-Dist: grpcio-tools<2.0.0,>=1.59.0
Requires-Dist: pika<2.0.0,>=1.3.0
Requires-Dist: rfdetr<2.0.0,>=1.2.0
Requires-Dist: boto3<2.0.0,>=1.28.0
Requires-Dist: pynvml<12.0.0,>=11.4.0
Requires-Dist: psutil<6.0.0,>=5.8.0
Requires-Dist: torch<3.0.0,>=2.0.0
Requires-Dist: torchvision<1.0.0,>=0.15.0
Requires-Dist: numpy<2.0.0,>=1.21.0
Requires-Dist: pillow<11.0.0,>=9.0.0
Requires-Dist: opencv-python<5.0.0,>=4.8.0
Requires-Dist: requests<3.0.0,>=2.31.0
Requires-Dist: tqdm<5.0.0,>=4.65.0
Provides-Extra: gpu
Requires-Dist: torch==2.3.1; extra == "gpu"
Requires-Dist: torchvision==0.18.1; extra == "gpu"
Provides-Extra: dev
Requires-Dist: pytest>=7.0.0; extra == "dev"
Requires-Dist: black>=22.0.0; extra == "dev"
Requires-Dist: isort>=5.10.0; extra == "dev"
Requires-Dist: mypy>=0.950; extra == "dev"
Requires-Dist: flake8>=4.0.0; extra == "dev"
Requires-Dist: pre-commit>=2.17.0; extra == "dev"
